aliyunsdkresourcesharing/__init__.py
aliyunsdkresourcesharing/endpoint.py
aliyunsdkresourcesharing/request/__init__.py
aliyunsdkresourcesharing/request/v20200110/AcceptResourceShareInvitationRequest.py
aliyunsdkresourcesharing/request/v20200110/AssociateResourceSharePermissionRequest.py
aliyunsdkresourcesharing/request/v20200110/AssociateResourceShareRequest.py
aliyunsdkresourcesharing/request/v20200110/ChangeResourceGroupRequest.py
aliyunsdkresourcesharing/request/v20200110/CheckSharingWithResourceDirectoryStatusRequest.py
aliyunsdkresourcesharing/request/v20200110/CreateResourceShareRequest.py
aliyunsdkresourcesharing/request/v20200110/DeleteResourceShareRequest.py
aliyunsdkresourcesharing/request/v20200110/DescribeRegionsRequest.py
aliyunsdkresourcesharing/request/v20200110/DisassociateResourceSharePermissionRequest.py
aliyunsdkresourcesharing/request/v20200110/DisassociateResourceShareRequest.py
aliyunsdkresourcesharing/request/v20200110/EnableSharingWithResourceDirectoryRequest.py
aliyunsdkresourcesharing/request/v20200110/GetPermissionRequest.py
aliyunsdkresourcesharing/request/v20200110/ListPermissionVersionsRequest.py
aliyunsdkresourcesharing/request/v20200110/ListPermissionsRequest.py
aliyunsdkresourcesharing/request/v20200110/ListResourceShareAssociationsRequest.py
aliyunsdkresourcesharing/request/v20200110/ListResourceShareInvitationsRequest.py
aliyunsdkresourcesharing/request/v20200110/ListResourceSharePermissionsRequest.py
aliyunsdkresourcesharing/request/v20200110/ListResourceSharesRequest.py
aliyunsdkresourcesharing/request/v20200110/ListSharedResourcesRequest.py
aliyunsdkresourcesharing/request/v20200110/ListSharedTargetsRequest.py
aliyunsdkresourcesharing/request/v20200110/RejectResourceShareInvitationRequest.py
aliyunsdkresourcesharing/request/v20200110/UpdateResourceShareRequest.py
aliyunsdkresourcesharing/request/v20200110/__init__.py
aliyun_python_sdk_resourcesharing-1.0.1.dist-info/LICENSE
aliyun_python_sdk_resourcesharing-1.0.1.dist-info/METADATA
aliyun_python_sdk_resourcesharing-1.0.1.dist-info/WHEEL
aliyun_python_sdk_resourcesharing-1.0.1.dist-info/top_level.txt
aliyun_python_sdk_resourcesharing-1.0.1.dist-info/RECORD
